poetry_import/__init__.py
poetry_import/main.py
poetry_import-0.1.0.dist-info/entry_points.txt
poetry_import-0.1.0.dist-info/WHEEL
poetry_import-0.1.0.dist-info/METADATA
poetry_import-0.1.0.dist-info/RECORD
