Metadata-Version: 2.1
Name: poetry-import
Version: 0.1.0
Summary: CLI utility that helps you migrate from Python pip requirements to Poetry pyproject.toml + poetry.lock.
Author: BrandonLWhite
Author-email: brandonlwhite@gmail.com
Requires-Python: >=3.9,<4.0
Classifier: Programming Language :: Python :: 3
Classifier: Programming Language :: Python :: 3.10
Classifier: Programming Language :: Python :: 3.9
Requires-Dist: packaging (>=21.3,<22.0)
Requires-Dist: pip (>=22.1.1,<23.0.0)
Requires-Dist: toml (>=0.10.2,<0.11.0)
